{
  "ComponentIndexes": {},
  "ControlUniqueGuids": {},
  "ControlUniqueIds": {
    "App": 1,
    "Available_DataCard1": 108,
    "Available_DataCard2": 132,
    "Body1": 95,
    "Body1_1": 94,
    "Body1_2": 174,
    "Body1_3": 175,
    "Body1_4": 15,
    "Body1_5": 16,
    "BrowseGallery1": 92,
    "BrowseGallery1_1": 172,
    "BrowseGallery1_2": 13,
    "Current Reservations Screen": 58,
    "Daily Reservations_Column1": 63,
    "daily_stats_button": 74,
    "DataCardKey1": 109,
    "DataCardKey10": 149,
    "DataCardKey11": 154,
    "DataCardKey12": 159,
    "DataCardKey2": 112,
    "DataCardKey3": 115,
    "DataCardKey4": 118,
    "DataCardKey5": 121,
    "DataCardKey6": 124,
    "DataCardKey7": 134,
    "DataCardKey8": 139,
    "DataCardKey9": 144,
    "DataCardValue1": 110,
    "DataCardValue10": 150,
    "DataCardValue11": 155,
    "DataCardValue12": 160,
    "DataCardValue2": 113,
    "DataCardValue3": 116,
    "DataCardValue4": 119,
    "DataCardValue5": 122,
    "DataCardValue6": 125,
    "DataCardValue7": 135,
    "DataCardValue8": 140,
    "DataCardValue9": 145,
    "DataTable1": 62,
    "Date_Column1": 65,
    "DatePicker1": 61,
    "DetailForm1": 107,
    "Dropdown1": 35,
    "EditForm1": 131,
    "ErrorMessage1": 136,
    "ErrorMessage2": 141,
    "ErrorMessage3": 146,
    "ErrorMessage4": 151,
    "ErrorMessage5": 156,
    "ErrorMessage6": 161,
    "galleryTemplate1_2": 93,
    "galleryTemplate1_3": 173,
    "galleryTemplate1_4": 14,
    "Home Screen": 67,
    "Icon1": 182,
    "Icon1_1": 88,
    "Icon1_2": 168,
    "Icon1_3": 9,
    "Icon1_4": 48,
    "Icon1_5": 28,
    "Icon1_6": 38,
    "IconAccept1": 128,
    "IconBackarrow1": 105,
    "IconCancel1": 129,
    "IconDelete1": 104,
    "IconEdit1": 103,
    "IconNewItem1": 86,
    "IconNewItem1_1": 166,
    "IconNewItem1_2": 7,
    "IconRefresh1": 84,
    "IconRefresh1_1": 164,
    "IconRefresh1_2": 5,
    "IconSortUpDown1": 85,
    "IconSortUpDown1_1": 165,
    "IconSortUpDown1_2": 6,
    "Image1": 69,
    "Image2": 81,
    "inventory": 79,
    "Inventory_BootsScreen": 82,
    "Inventory_DetailScreen": 101,
    "Inventory_EditScreen": 126,
    "inventory_helmetButton": 183,
    "Inventory_HelmetScreen": 162,
    "Inventory_HomeScreen": 181,
    "inventory_polesButton": 186,
    "inventory_skiBootsButton": 184,
    "inventory_skiesButton": 185,
    "Inventory_SkiScreen": 3,
    "inventory_SnowboardBootsButton": 188,
    "inventory_snowboardsButton": 187,
    "Item_DataCard1": 111,
    "Item_DataCard2": 137,
    "Label1": 72,
    "Label2": 76,
    "Label2_1": 75,
    "Label3": 50,
    "Label3_1": 54,
    "Label3_2": 55,
    "Label3_3": 30,
    "Label3_4": 40,
    "Label3_5": 41,
    "Label4": 60,
    "Label5": 47,
    "Label5_1": 49,
    "Label5_2": 27,
    "Label5_3": 29,
    "Label5_4": 37,
    "Label5_5": 39,
    "Label6": 70,
    "LblAppName1": 87,
    "LblAppName1_1": 167,
    "LblAppName1_2": 8,
    "LblAppName2": 106,
    "LblAppName3": 130,
    "Lifetime Stats": 22,
    "lifetime_stats_button": 80,
    "newCust": 73,
    "newCust_1": 52,
    "newCust_2": 32,
    "newCust_3": 42,
    "NewCustomer_GetAgeScreen": 23,
    "NewCustomer_GetEmailScreen": 24,
    "NewCustomer_GetHeightScreen": 33,
    "NewCustomer_GetNameScreen": 44,
    "NextArrow1_2": 98,
    "NextArrow1_3": 178,
    "NextArrow1_4": 19,
    "Out of service_DataCard1": 114,
    "Out of service_DataCard2": 142,
    "Rectangle1": 71,
    "Rectangle11": 91,
    "Rectangle11_1": 171,
    "Rectangle11_2": 12,
    "Rectangle2": 59,
    "Rectangle3": 45,
    "Rectangle3_1": 46,
    "Rectangle3_2": 25,
    "Rectangle3_3": 26,
    "Rectangle3_4": 34,
    "Rectangle3_5": 36,
    "RectQuickActionBar1": 83,
    "RectQuickActionBar1_1": 163,
    "RectQuickActionBar1_2": 4,
    "RectQuickActionBar2": 102,
    "RectQuickActionBar3": 127,
    "Rented_DataCard1": 117,
    "Rented_DataCard2": 147,
    "returnCust": 77,
    "SearchIcon1": 90,
    "SearchIcon1_1": 170,
    "SearchIcon1_2": 11,
    "Season Renters_Column1": 64,
    "Season Stats": 57,
    "season_stats_button": 78,
    "Separator1_2": 100,
    "Separator1_3": 180,
    "Separator1_4": 21,
    "Size_DataCard1": 120,
    "Size_DataCard2": 152,
    "StarVisible1": 133,
    "StarVisible2": 138,
    "StarVisible3": 143,
    "StarVisible4": 148,
    "StarVisible5": 153,
    "StarVisible6": 158,
    "Subtitle1": 99,
    "Subtitle1_1": 179,
    "Subtitle1_2": 20,
    "TextInput1": 51,
    "TextInput1_1": 53,
    "TextInput1_2": 56,
    "TextInput1_3": 31,
    "TextInput1_5": 43,
    "TextSearchBox1": 89,
    "TextSearchBox1_1": 169,
    "TextSearchBox1_2": 10,
    "Timer1": 68,
    "Title1": 97,
    "Title1_1": 96,
    "Title1_2": 176,
    "Title1_3": 177,
    "Title1_4": 17,
    "Title1_5": 18,
    "Total Quantity_DataCard1": 123,
    "Total Quantity_DataCard2": 157,
    "Total Renters_Column1": 66
  },
  "FunctionParamsInvariantScripts": {},
  "FunctionParamsInvariantScriptsOnInstances": {},
  "HeaderLastSavedDateTimeUTC": "04/07/2023 17:30:41",
  "IsLegacyComponentAllowGlobalScopeCase": false,
  "LocalConnectionIDReferences": {
    "ae857b0b-141e-42ac-ba1d-2e7a3f19f5c8": "\"/providers/microsoft.powerapps/apis/shared_onedriveforbusiness/connections/98a2109870984f41819cfe93a3c99300\"",
    "c9997293-e995-4d98-945d-f016be4cdd70": "\"/providers/microsoft.powerapps/apis/shared_onedrive/connections/516e5a6bcd2a4c779a08144e963f3e43\"",
    "e5711ea5-5273-4ffe-a547-9a56381709b1": "\"/providers/microsoft.powerapps/apis/shared_excel/connections/9b5c928128b84804a4e7f1b0304ebd23\"",
    "ed0a6f5a-4b43-497f-95bc-661c0a4c40ed": "\"/providers/microsoft.powerapps/apis/shared_excel/connections/9913e51c7dae4777b5d6b965eaa06fa8\""
  },
  "LocalDatabaseReferencesAsEmpty": false,
  "LocalResourceFileNames": {
    "Mount-Ripley-Logo-sm": "0001.jpg",
    "steezy logo": "0002.png"
  },
  "LocalResourceRootPaths": {
    "Mount-Ripley-Logo-sm": "https://docserverpwaprodeus.blob.core.windows.net/b3fa2775-8ba3-4448-8af8-e9274a6f0076-1/resource/Assets0Images00001.jpg?sv=2018-03-28&sr=b&sig=xUQIwfFT%2FIbdBaSCiKyG5CvEA7kFu%2Bziu%2FJ0OoFSNts%3D&spr=https&se=2023-04-08T17%3A42%3A55Z&sp=r",
    "steezy logo": "https://docserverpwaprodeus.blob.core.windows.net/b3fa2775-8ba3-4448-8af8-e9274a6f0076-1/resource/Assets0Images00002.png?sv=2018-03-28&sr=b&sig=vYgUmkMrJxqIMqXUzjzX2%2BXC2NZ37kOePT8GSkfRkSU%3D&spr=https&se=2023-04-08T17%3A42%3A55Z&sp=r"
  },
  "OrderComponentMetadata": {},
  "OrderComponentTemplate": {},
  "OrderDataSource": {
    "Boots": 0,
    "CustomGallerySample": 1,
    "DropDownSample": 2,
    "Helmet": 3,
    "Table1": 4,
    "Table1_1": 7,
    "Table1_2": 8,
    "Table1_3": 9,
    "Table1_4": 10,
    "Table14": 5,
    "Table15": 6
  },
  "OrderGroupControls": {},
  "OrderPcfTemplate": {},
  "OrderTemplate": {},
  "OrderXMLTemplate": {
    "button": 5,
    "datepicker": 7,
    "dropdown": 6,
    "form": 11,
    "formViewer": 10,
    "gallery": 4,
    "icon": 1,
    "image": 9,
    "label": 2,
    "rectangle": 0,
    "text": 3,
    "timer": 8
  },
  "OverridablePropertiesEntry": {
    "App": {},
    "Available_DataCard1": {},
    "Available_DataCard2": {},
    "Body1": {},
    "Body1_1": {},
    "Body1_2": {},
    "Body1_3": {},
    "Body1_4": {},
    "Body1_5": {},
    "BrowseGallery1": {},
    "BrowseGallery1_1": {},
    "BrowseGallery1_2": {},
    "Current Reservations Screen": {},
    "Daily Reservations_Column1": {},
    "daily_stats_button": {},
    "DataCardKey1": {},
    "DataCardKey10": {},
    "DataCardKey11": {},
    "DataCardKey12": {},
    "DataCardKey2": {},
    "DataCardKey3": {},
    "DataCardKey4": {},
    "DataCardKey5": {},
    "DataCardKey6": {},
    "DataCardKey7": {},
    "DataCardKey8": {},
    "DataCardKey9": {},
    "DataCardValue1": {},
    "DataCardValue10": {},
    "DataCardValue11": {},
    "DataCardValue12": {},
    "DataCardValue2": {},
    "DataCardValue3": {},
    "DataCardValue4": {},
    "DataCardValue5": {},
    "DataCardValue6": {},
    "DataCardValue7": {},
    "DataCardValue8": {},
    "DataCardValue9": {},
    "DataTable1": {},
    "Date_Column1": {},
    "DatePicker1": {},
    "DetailForm1": {},
    "Dropdown1": {},
    "EditForm1": {},
    "ErrorMessage1": {},
    "ErrorMessage2": {},
    "ErrorMessage3": {},
    "ErrorMessage4": {},
    "ErrorMessage5": {},
    "ErrorMessage6": {},
    "galleryTemplate1_2": {},
    "galleryTemplate1_3": {},
    "galleryTemplate1_4": {},
    "Home Screen": {},
    "Icon1": {},
    "Icon1_1": {},
    "Icon1_2": {},
    "Icon1_3": {},
    "Icon1_4": {},
    "Icon1_5": {},
    "Icon1_6": {},
    "IconAccept1": {},
    "IconBackarrow1": {},
    "IconCancel1": {},
    "IconDelete1": {},
    "IconEdit1": {},
    "IconNewItem1": {},
    "IconNewItem1_1": {},
    "IconNewItem1_2": {},
    "IconRefresh1": {},
    "IconRefresh1_1": {},
    "IconRefresh1_2": {},
    "IconSortUpDown1": {},
    "IconSortUpDown1_1": {},
    "IconSortUpDown1_2": {},
    "Image1": {},
    "Image2": {},
    "inventory": {},
    "Inventory_BootsScreen": {},
    "Inventory_DetailScreen": {},
    "Inventory_EditScreen": {},
    "inventory_helmetButton": {},
    "Inventory_HelmetScreen": {},
    "Inventory_HomeScreen": {},
    "inventory_polesButton": {},
    "inventory_skiBootsButton": {},
    "inventory_skiesButton": {},
    "Inventory_SkiScreen": {},
    "inventory_SnowboardBootsButton": {},
    "inventory_snowboardsButton": {},
    "Item_DataCard1": {},
    "Item_DataCard2": {},
    "Label1": {},
    "Label2": {},
    "Label2_1": {},
    "Label3": {},
    "Label3_1": {},
    "Label3_2": {},
    "Label3_3": {},
    "Label3_4": {},
    "Label3_5": {},
    "Label4": {},
    "Label5": {},
    "Label5_1": {},
    "Label5_2": {},
    "Label5_3": {},
    "Label5_4": {},
    "Label5_5": {},
    "Label6": {},
    "LblAppName1": {},
    "LblAppName1_1": {},
    "LblAppName1_2": {},
    "LblAppName2": {},
    "LblAppName3": {},
    "Lifetime Stats": {},
    "lifetime_stats_button": {},
    "newCust": {},
    "newCust_1": {},
    "newCust_2": {},
    "newCust_3": {},
    "NewCustomer_GetAgeScreen": {},
    "NewCustomer_GetEmailScreen": {},
    "NewCustomer_GetHeightScreen": {},
    "NewCustomer_GetNameScreen": {},
    "NextArrow1_2": {},
    "NextArrow1_3": {},
    "NextArrow1_4": {},
    "Out of service_DataCard1": {},
    "Out of service_DataCard2": {},
    "Rectangle1": {},
    "Rectangle11": {},
    "Rectangle11_1": {},
    "Rectangle11_2": {},
    "Rectangle2": {},
    "Rectangle3": {},
    "Rectangle3_1": {},
    "Rectangle3_2": {},
    "Rectangle3_3": {},
    "Rectangle3_4": {},
    "Rectangle3_5": {},
    "RectQuickActionBar1": {},
    "RectQuickActionBar1_1": {},
    "RectQuickActionBar1_2": {},
    "RectQuickActionBar2": {},
    "RectQuickActionBar3": {},
    "Rented_DataCard1": {},
    "Rented_DataCard2": {},
    "returnCust": {},
    "SearchIcon1": {},
    "SearchIcon1_1": {},
    "SearchIcon1_2": {},
    "Season Renters_Column1": {},
    "Season Stats": {},
    "season_stats_button": {},
    "Separator1_2": {},
    "Separator1_3": {},
    "Separator1_4": {},
    "Size_DataCard1": {},
    "Size_DataCard2": {},
    "StarVisible1": {},
    "StarVisible2": {},
    "StarVisible3": {},
    "StarVisible4": {},
    "StarVisible5": {},
    "StarVisible6": {},
    "Subtitle1": {},
    "Subtitle1_1": {},
    "Subtitle1_2": {},
    "TextInput1": {},
    "TextInput1_1": {},
    "TextInput1_2": {},
    "TextInput1_3": {},
    "TextInput1_5": {},
    "TextSearchBox1": {},
    "TextSearchBox1_1": {},
    "TextSearchBox1_2": {},
    "Timer1": {},
    "Title1": {},
    "Title1_1": {},
    "Title1_2": {},
    "Title1_3": {},
    "Title1_4": {},
    "Title1_5": {},
    "Total Quantity_DataCard1": {},
    "Total Quantity_DataCard2": {},
    "Total Renters_Column1": {}
  },
  "PCFDynamicSchemaForIRRetrievalEntry": {},
  "PCFTemplateEntry": {},
  "PublishOrderIndices": {
    "App": 0,
    "Available_DataCard1": 52,
    "Available_DataCard2": 76,
    "Body1": 39,
    "Body1_1": 38,
    "Body1_2": 118,
    "Body1_3": 119,
    "Body1_4": 145,
    "Body1_5": 146,
    "BrowseGallery1": 36,
    "BrowseGallery1_1": 116,
    "BrowseGallery1_2": 143,
    "Current Reservations Screen": 2,
    "Daily Reservations_Column1": 7,
    "daily_stats_button": 18,
    "DataCardKey1": 58,
    "DataCardKey10": 95,
    "DataCardKey11": 99,
    "DataCardKey12": 103,
    "DataCardKey2": 60,
    "DataCardKey3": 62,
    "DataCardKey4": 64,
    "DataCardKey5": 66,
    "DataCardKey6": 68,
    "DataCardKey7": 83,
    "DataCardKey8": 87,
    "DataCardKey9": 91,
    "DataCardValue1": 59,
    "DataCardValue10": 96,
    "DataCardValue11": 100,
    "DataCardValue12": 104,
    "DataCardValue2": 61,
    "DataCardValue3": 63,
    "DataCardValue4": 65,
    "DataCardValue5": 67,
    "DataCardValue6": 69,
    "DataCardValue7": 84,
    "DataCardValue8": 88,
    "DataCardValue9": 92,
    "DataTable1": 6,
    "Date_Column1": 9,
    "DatePicker1": 5,
    "DetailForm1": 51,
    "Dropdown1": 165,
    "EditForm1": 75,
    "ErrorMessage1": 85,
    "ErrorMessage2": 89,
    "ErrorMessage3": 93,
    "ErrorMessage4": 97,
    "ErrorMessage5": 101,
    "ErrorMessage6": 105,
    "galleryTemplate1_2": 37,
    "galleryTemplate1_3": 117,
    "galleryTemplate1_4": 144,
    "Home Screen": 11,
    "Icon1": 126,
    "Icon1_1": 32,
    "Icon1_2": 112,
    "Icon1_3": 139,
    "Icon1_4": 178,
    "Icon1_5": 158,
    "Icon1_6": 168,
    "IconAccept1": 72,
    "IconBackarrow1": 49,
    "IconCancel1": 73,
    "IconDelete1": 48,
    "IconEdit1": 47,
    "IconNewItem1": 30,
    "IconNewItem1_1": 110,
    "IconNewItem1_2": 137,
    "IconRefresh1": 28,
    "IconRefresh1_1": 108,
    "IconRefresh1_2": 135,
    "IconSortUpDown1": 29,
    "IconSortUpDown1_1": 109,
    "IconSortUpDown1_2": 136,
    "Image1": 13,
    "Image2": 25,
    "inventory": 23,
    "Inventory_BootsScreen": 26,
    "Inventory_DetailScreen": 45,
    "Inventory_EditScreen": 70,
    "inventory_helmetButton": 127,
    "Inventory_HelmetScreen": 106,
    "Inventory_HomeScreen": 125,
    "inventory_polesButton": 130,
    "inventory_skiBootsButton": 128,
    "inventory_skiesButton": 129,
    "Inventory_SkiScreen": 133,
    "inventory_SnowboardBootsButton": 132,
    "inventory_snowboardsButton": 131,
    "Item_DataCard1": 53,
    "Item_DataCard2": 77,
    "Label1": 16,
    "Label2": 20,
    "Label2_1": 19,
    "Label3": 180,
    "Label3_1": 184,
    "Label3_2": 185,
    "Label3_3": 160,
    "Label3_4": 170,
    "Label3_5": 171,
    "Label4": 4,
    "Label5": 177,
    "Label5_1": 179,
    "Label5_2": 157,
    "Label5_3": 159,
    "Label5_4": 167,
    "Label5_5": 169,
    "Label6": 14,
    "LblAppName1": 31,
    "LblAppName1_1": 111,
    "LblAppName1_2": 138,
    "LblAppName2": 50,
    "LblAppName3": 74,
    "Lifetime Stats": 152,
    "lifetime_stats_button": 24,
    "newCust": 17,
    "newCust_1": 182,
    "newCust_2": 162,
    "newCust_3": 172,
    "NewCustomer_GetAgeScreen": 153,
    "NewCustomer_GetEmailScreen": 154,
    "NewCustomer_GetHeightScreen": 163,
    "NewCustomer_GetNameScreen": 174,
    "NextArrow1_2": 42,
    "NextArrow1_3": 122,
    "NextArrow1_4": 149,
    "Out of service_DataCard1": 54,
    "Out of service_DataCard2": 78,
    "Rectangle1": 15,
    "Rectangle11": 35,
    "Rectangle11_1": 115,
    "Rectangle11_2": 142,
    "Rectangle2": 3,
    "Rectangle3": 175,
    "Rectangle3_1": 176,
    "Rectangle3_2": 155,
    "Rectangle3_3": 156,
    "Rectangle3_4": 164,
    "Rectangle3_5": 166,
    "RectQuickActionBar1": 27,
    "RectQuickActionBar1_1": 107,
    "RectQuickActionBar1_2": 134,
    "RectQuickActionBar2": 46,
    "RectQuickActionBar3": 71,
    "Rented_DataCard1": 55,
    "Rented_DataCard2": 79,
    "returnCust": 21,
    "SearchIcon1": 34,
    "SearchIcon1_1": 114,
    "SearchIcon1_2": 141,
    "Season Renters_Column1": 8,
    "Season Stats": 187,
    "season_stats_button": 22,
    "Separator1_2": 44,
    "Separator1_3": 124,
    "Separator1_4": 151,
    "Size_DataCard1": 56,
    "Size_DataCard2": 80,
    "StarVisible1": 82,
    "StarVisible2": 86,
    "StarVisible3": 90,
    "StarVisible4": 94,
    "StarVisible5": 98,
    "StarVisible6": 102,
    "Subtitle1": 43,
    "Subtitle1_1": 123,
    "Subtitle1_2": 150,
    "TextInput1": 181,
    "TextInput1_1": 183,
    "TextInput1_2": 186,
    "TextInput1_3": 161,
    "TextInput1_5": 173,
    "TextSearchBox1": 33,
    "TextSearchBox1_1": 113,
    "TextSearchBox1_2": 140,
    "Timer1": 12,
    "Title1": 41,
    "Title1_1": 40,
    "Title1_2": 120,
    "Title1_3": 121,
    "Title1_4": 147,
    "Title1_5": 148,
    "Total Quantity_DataCard1": 57,
    "Total Quantity_DataCard2": 81,
    "Total Renters_Column1": 10
  },
  "ResourcesJsonIndices": {
    "Image-Mount-Ripley-Logo-sm": 1,
    "Image-SampleImage": 0,
    "Image-steezy logo": 2
  },
  "RuleScreenIdWithoutScreen": {},
  "TemplateVersions": {},
  "VolatileProperties": {
    "AnalysisLoadTime": 0.5357151,
    "ControlCount": {
      "button": 15,
      "dataTable": 1,
      "dataTableColumn": 4,
      "datepicker": 1,
      "dropdown": 1,
      "form": 1,
      "formViewer": 1,
      "gallery": 3,
      "galleryTemplate": 3,
      "icon": 27,
      "image": 2,
      "label": 67,
      "rectangle": 19,
      "screen": 14,
      "text": 14,
      "timer": 1,
      "typedDataCard": 12
    },
    "DeserializationLoadTime": 0.8845181,
    "ErrorCount": 0
  },
  "WasLocalDatabaseReferencesEmpty": true
}